git_remote_run/__init__.py
git_remote_run/remote.py
git_remote_run-1.2.dist-info/LICENSE
git_remote_run-1.2.dist-info/METADATA
git_remote_run-1.2.dist-info/WHEEL
git_remote_run-1.2.dist-info/entry_points.txt
git_remote_run-1.2.dist-info/top_level.txt
git_remote_run-1.2.dist-info/RECORD
