Metadata-Version: 2.1
Name: git-remote-run
Version: 1.2
Summary: Allows running custom commands on a git remote.
Home-page: https://github.com/rczajka/git-remote-run
Author: Radek Czajka
Author-email: rczajka@rczajka.pl
License: MIT
Platform: UNKNOWN
Classifier: Development Status :: 3 - Alpha
Classifier: Environment :: Console
Classifier: License :: OSI Approved :: MIT License
Classifier: Programming Language :: Python :: 3
Classifier: Topic :: Software Development :: Version Control :: Git
Requires-Python: >=3.3
